testextension/__init__.py
testextension/_version.py
testextension/labextension/package.json
testextension/labextension/static/568.f96ab05e9fce49f64b4d.js
testextension/labextension/static/747.bf26e633fc695373f314.js
testextension/labextension/static/remoteEntry.809132b72768810c5523.js
testextension/labextension/static/style.js
testextension/labextension/static/third-party-licenses.json
testextension-0.1.0.data/data/share/jupyter/labextensions/testextension/install.json
testextension-0.1.0.data/data/share/jupyter/labextensions/testextension/package.json
testextension-0.1.0.data/data/share/jupyter/labextensions/testextension/static/568.f96ab05e9fce49f64b4d.js
testextension-0.1.0.data/data/share/jupyter/labextensions/testextension/static/747.bf26e633fc695373f314.js
testextension-0.1.0.data/data/share/jupyter/labextensions/testextension/static/remoteEntry.809132b72768810c5523.js
testextension-0.1.0.data/data/share/jupyter/labextensions/testextension/static/style.js
testextension-0.1.0.data/data/share/jupyter/labextensions/testextension/static/third-party-licenses.json
testextension-0.1.0.dist-info/LICENSE
testextension-0.1.0.dist-info/METADATA
testextension-0.1.0.dist-info/WHEEL
testextension-0.1.0.dist-info/top_level.txt
testextension-0.1.0.dist-info/RECORD
